<?xml version="1.0" encoding="UTF-8" standalone="yes"?>
<publish xmlns:xsi="http://www.w3.org/2001/XMLSchema-instance">
	<device>
		<name>AP_0_1</name>
		<posx>2357.67</posx>
		<posy>923.53</posy>
	</device>
	<device>
		<name>AP_0_2</name>
		<posx>2303.32</posx>
		<posy>928.66</posy>
	</device>
	<device>
		<name>AP_0_3</name>
		<posx>2194.6</posx>
		<posy>930.6</posy>
	</device>
	<device>
		<name>AP_0_4</name>
		<posx>2051.16</posx>
		<posy>931.47</posy>
	</device>
	<device>
		<name>AP_0_5</name>
		<posx>1943.35</posx>
		<posy>934.96</posy>
	</device>
	<device>
		<name>AP_0_6</name>
		<posx>1821.8</posx>
		<posy>939.49</posy>
	</device>
	<device>
		<name>AP_0_7</name>
		<posx>1679.73</posx>
		<posy>1039.31</posy>
	</device>
	<device>
		<name>AP_0_8</name>
		<posx>1563.73</posx>
		<posy>1050.31</posy>
	</device>
	<device>
		<name>AP_0_9</name>
		<posx>1458.73</posx>
		<posy>975.31</posy>
	</device>
	<device>
		<name>AP_0_10</name>
		<posx>1396.23</posx>
		<posy>882.56</posy>
	</device>
	<device>
		<name>AP_0_11</name>
		<posx>1409.73</posx>
		<posy>762.31</posy>
	</device>
	<device>
		<name>AP_0_14</name>
		<posx>1540.98</posx>
		<posy>662.06</posy>
	</device>
	<device>
		<name>AP_0_13</name>
		<posx>1413.52</posx>
		<posy>630.31</posy>
	</device>
	<device>
		<name>AP_0_12</name>
		<posx>1255.93</posx>
		<posy>589.72</posy>
	</device>
	<device>
		<name>AP_0_15</name>
		<posx>1097.94</posx>
		<posy>567.28</posy>
	</device>
	<device>
		<name>AP_0_16</name>
		<posx>966.43</posx>
		<posy>570.4</posy>
	</device>
	<device>
		<name>AP_0_17</name>
		<posx>882.93</posx>
		<posy>707.81</posy>
	</device>
	<device>
		<name>AP_0_18</name>
		<posx>728.93</posx>
		<posy>859.21</posy>
	</device>
	<device>
		<name>AP_0_19</name>
		<posx>553.24</posx>
		<posy>890.5</posy>
	</device>
	<device>
		<name>AP_0_20</name>
		<posx>441.19</posx>
		<posy>824</posy>
	</device>
	<device>
		<name>AP_0_21</name>
		<posx>459.93</posx>
		<posy>669.5</posy>
	</device>
	<device>
		<name>AP_0_22</name>
		<posx>599.93</posx>
		<posy>588.45</posy>
	</device>
	<device>
		<name>AP_0_23</name>
		<posx>694.93</posx>
		<posy>683</posy>
	</device>
	<device>
		<name>AP_0_24</name>
		<posx>756.43</posx>
		<posy>549.18</posy>
	</device>
	<device>
		<name>AP_0_25</name>
		<posx>870.18</posx>
		<posy>538.68</posy>
	</device>
	<device>
		<name>AP_0_26</name>
		<posx>1109.67</posx>
		<posy>423.73</posy>
	</device>
	<device>
		<name>AP_0_27</name>
		<posx>1251.92</posx>
		<posy>427.31</posy>
	</device>
	<device>
		<name>AP_0_28</name>
		<posx>1380.3</posx>
		<posy>421.62</posy>
	</device>
	<device>
		<name>AP_0_29</name>
		<posx>1522.18</posx>
		<posy>423.51</posy>
	</device>
	<device>
		<name>AP_0_30</name>
		<posx>1669.8</posx>
		<posy>408.12</posy>
	</device>
	<device>
		<name>AP_0_31</name>
		<posx>1815.63</posx>
		<posy>410.62</posy>
	</device>
	<device>
		<name>AP_0_32</name>
		<posx>1986.18</posx>
		<posy>412.82</posy>
	</device>
	<device>
		<name>AP_0_33</name>
		<posx>2094.74</posx>
		<posy>490.87</posy>
	</device>
	<device>
		<name>AP_0_34</name>
		<posx>2161.89</posx>
		<posy>622.86</posy>
	</device>
	<device>
		<name>AP_0_35</name>
		<posx>2164.33</posx>
		<posy>784.79</posy>
	</device>
	<device>
		<name>AP_0_36</name>
		<posx>2034.9</posx>
		<posy>788.75</posy>
	</device>
	<device>
		<name>AP_0_37</name>
		<posx>1961.31</posx>
		<posy>661.16</posy>
	</device>
	<device>
		<name>AP_0_38</name>
		<posx>1771.73</posx>
		<posy>566.41</posy>
	</device>
	<device>
		<name>AP_0_39</name>
		<posx>1628.99</posx>
		<posy>575.91</posy>
	</device>
	<device>
		<name>AP_0_40</name>
		<posx>707.94</posx>
		<posy>292.14</posy>
	</device>
	<device>
		<name>AP_0_41</name>
		<posx>691.81</posx>
		<posy>464.39</posy>
	</device>
	<device>
		<name>AP_0_42</name>
		<posx>694.86</posx>
		<posy>604.29</posy>
	</device>
	<device>
		<name>AP_0_43</name>
		<posx>616.31</posx>
		<posy>732.17</posy>
	</device>
	<device>
		<name>AP_0_44</name>
		<posx>485.22</posx>
		<posy>831.64</posy>
	</device>
	<device>
		<name>AP_0_45</name>
		<posx>493.39</posx>
		<posy>1003.68</posy>
	</device>
	<device>
		<name>AP_0_46</name>
		<posx>490.87</posx>
		<posy>1152.18</posy>
	</device>
	<device>
		<name>AP_0_47</name>
		<posx>494.97</posx>
		<posy>1294.27</posy>
	</device>
	<device>
		<name>AP_0_48</name>
		<posx>483.74</posx>
		<posy>1414.92</posy>
	</device>
	<device>
		<name>AP_0_49</name>
		<posx>489.12</posx>
		<posy>1561.46</posy>
	</device>
	<device>
		<name>AP_0_50</name>
		<posx>492.48</posx>
		<posy>1692.17</posy>
	</device>
	<device>
		<name>AP_0_51</name>
		<posx>604.58</posx>
		<posy>1698.39</posy>
	</device>
	<device>
		<name>AP_0_52</name>
		<posx>695.69</posx>
		<posy>1593.11</posy>
	</device>
	<device>
		<name>AP_0_53</name>
		<posx>647.81</posx>
		<posy>1471.79</posy>
	</device>
	<device>
		<name>AP_0_54</name>
		<posx>788.43</posx>
		<posy>1470.26</posy>
	</device>
	<device>
		<name>AP_0_55</name>
		<posx>617.95</posx>
		<posy>1200.34</posy>
	</device>
	<device>
		<name>AP_0_56</name>
		<posx>779.92</posx>
		<posy>1205.87</posy>
	</device>
	<device>
		<name>AP_0_57</name>
		<posx>617.28</posx>
		<posy>1005.62</posy>
	</device>
	<device>
		<name>AP_0_58</name>
		<posx>767.15</posx>
		<posy>1000.24</posy>
	</device>
	<device>
		<name>AP_0_59</name>
		<posx>688.52</posx>
		<posy>870.54</posy>
	</device>
	<device>
		<name>AP_0_60</name>
		<posx>796.05</posx>
		<posy>722.69</posy>
	</device>
	<device>
		<name>AP_0_61</name>
		<posx>924.41</posx>
		<posy>406.44</posy>
	</device>
	<device>
		<name>AP_0_62</name>
		<posx>921.05</posx>
		<posy>511.88</posy>
	</device>
	<device>
		<name>AP_0_63</name>
		<posx>924.51</posx>
		<posy>717.78</posy>
	</device>
	<device>
		<name>AP_0_64</name>
		<posx>925.29</posx>
		<posy>856.22</posy>
	</device>
	<device>
		<name>AP_0_65</name>
		<posx>918.77</posx>
		<posy>1014.15</posy>
	</device>
	<device>
		<name>AP_0_66</name>
		<posx>919.2</posx>
		<posy>1141.69</posy>
	</device>
	<device>
		<name>AP_0_67</name>
		<posx>926.81</posx>
		<posy>1292.9</posy>
	</device>
	<device>
		<name>AP_0_68</name>
		<posx>917.5</posx>
		<posy>1409.8</posy>
	</device>
	<device>
		<name>AP_0_69</name>
		<posx>922.88</posx>
		<posy>1560.37</posy>
	</device>
	<device>
		<name>AP_0_70</name>
		<posx>733.92</posx>
		<posy>1694.98</posy>
	</device>
	<device>
		<name>AP_0_71</name>
		<posx>874.69</posx>
		<posy>1690.28</posy>
	</device>
	<device>
		<name>AP_0_72</name>
		<posx>1020.1</posx>
		<posy>1691.8</posy>
	</device>
</publish>